wechsel/__init__.py
wechsel/download_utils.py
wechsel-0.0.4.dist-info/LICENSE
wechsel-0.0.4.dist-info/METADATA
wechsel-0.0.4.dist-info/WHEEL
wechsel-0.0.4.dist-info/top_level.txt
wechsel-0.0.4.dist-info/RECORD
