Metadata-Version: 2.1
Name: wechsel
Version: 0.0.4
Summary: Code for WECHSEL: Effective initialization of subword embeddings for cross-lingual transfer of monolingual language models.
Home-page: https://github.com/cpjku/wechsel
Author: Benjamin Minixhofer
Author-email: bminixhofer@gmail.com
License: MIT
Platform: UNKNOWN
Requires-Python: >=3.6.0
License-File: LICENSE
Requires-Dist: requests (>=2.26.0)
Requires-Dist: gensim (>=4.1.2)
Requires-Dist: fasttext (>=0.9.2)
Requires-Dist: datasets (>=1.16.1)
Requires-Dist: tqdm (>=4.62.3)
Requires-Dist: scipy (>=1.7.3)
Requires-Dist: scikit-learn (>=1.0.1)
Requires-Dist: nltk (>=3.6.5)
